sfdata_stream_tutorial/__init__.py
sfdata_stream_tutorial/__main__.py
sfdata_stream_tutorial/_generate.py
sfdata_stream_tutorial-0.1.1.dist-info/WHEEL
sfdata_stream_tutorial-0.1.1.dist-info/METADATA
sfdata_stream_tutorial-0.1.1.dist-info/RECORD
