Metadata-Version: 2.1
Name: sfdata-stream-tutorial
Version: 0.1.1
Summary: 
License: MIT
Author: Kaj Siebert
Author-email: kaj@k-si.com
Requires-Python: >=3.8,<4.0
Classifier: License :: OSI Approved :: MIT License
Classifier: Programming Language :: Python :: 3
Classifier: Programming Language :: Python :: 3.10
Classifier: Programming Language :: Python :: 3.8
Classifier: Programming Language :: Python :: 3.9
Requires-Dist: Faker (>=13.3.3,<14.0.0)
Requires-Dist: click (>=8.0.4,<9.0.0)
Requires-Dist: sfdata-stream-parser (>=0.2.0,<0.3.0)
Requires-Dist: tablib[xlsx] (>=3.2.0,<4.0.0)
